[
  [
    { "lyrics": "עצמאי", "chords": "Am" },
    { "lyrics": "בשטח" },
    { "lyrics": "לא", "chords": "D" },
    { "lyrics": "צריך" },
    { "lyrics": "טובות", "chords": "G" }
  ],
  [
    { "lyrics": "הוא", "chords": "C" },
    { "lyrics": "אפילו" },
    { "lyrics": "לא" },
    { "lyrics": "מחזיק", "chords": "F#m" }
  ],
  [{ "lyrics": "רשימת", "chords": "Bm" }, { "lyrics": "כתובות" }],
  [
    { "lyrics": "שרוך", "chords": "G7" },
    { "lyrics": "אחד", "chords": "C" },
    { "lyrics": "קרוע" }
  ],
  [
    { "lyrics": "שרוך", "chords": "Em" },
    { "lyrics": "אחד" },
    { "lyrics": "כבר", "chords": "Am" },
    { "lyrics": "אין" }
  ],
  [
    { "lyrics": "פעם", "chords": "D" },
    { "lyrics": "צעד" },
    { "lyrics": "לא", "chords": "E" },
    { "lyrics": "בטוח" }
  ],
  [{ "lyrics": "פעם", "chords": "G" }, { "lyrics": "צעד" }, { "lyrics": "כן" }],
  [
    { "lyrics": "הולך" },
    { "lyrics": "בטל,", "chords": "F#m" },
    { "lyrics": "הולך", "chords": "D" }
  ],
  [{ "lyrics": "הולך" }, { "lyrics": "בטל" }],
  [
    { "lyrics": "הרחובות", "chords": "Bm" },
    { "lyrics": "נותנים" },
    { "lyrics": "לו" }
  ],
  [
    { "lyrics": "זמן", "chords": "Am" },
    { "lyrics": "בלי" },
    { "lyrics": "חשבונות" }
  ],
  [
    { "lyrics": "פה", "chords": "G7" },
    { "lyrics": "ושם" },
    { "lyrics": "הוא", "chords": "D" },
    { "lyrics": "מגלגל" }
  ],
  [{ "lyrics": "סימטאות", "chords": "C" }, { "lyrics": "קטנות" }],
  [{ "lyrics": "מחפש", "chords": "F#m" }, { "lyrics": "בחושך" }],
  [{ "lyrics": "חומר", "chords": "E" }, { "lyrics": "ללחישה" }],
  [{ "lyrics": "למקרה", "chords": "Am" }, { "lyrics": "שייתקל" }],
  [{ "lyrics": "באוזני", "chords": "Bm" }, { "lyrics": "אישה" }],
  [
    { "lyrics": "הולך" },
    { "lyrics": "בטל,", "chords": "D" },
    { "lyrics": "הולך", "chords": "G" }
  ],
  [{ "lyrics": "הולך" }, { "lyrics": "בטל" }],
  [
    { "lyrics": "בעיניו", "chords": "Em" },
    { "lyrics": "יש" },
    { "lyrics": "\"מה", "chords": "C" },
    { "lyrics": "זה" },
    { "lyrics": "כל", "chords": "G7" },
    { "lyrics": "זה\"?" }
  ],
  [
    { "lyrics": "הוא", "chords": "F#m" },
    { "lyrics": "גם" },
    { "lyrics": "קצת", "chords": "Bm" },
    { "lyrics": "רעב" }
  ],
  [
    { "lyrics": "אולי", "chords": "Am" },
    { "lyrics": "גם" },
    { "lyrics": "קצת" },
    { "lyrics": "הוא", "chords": "D" },
    { "lyrics": "נהנה" }
  ],
  [{ "lyrics": "להרגיש", "chords": "Em" }, { "lyrics": "כאב" }],
  [{ "lyrics": "מחפש", "chords": "G" }, { "lyrics": "בחושך" }],
  [{ "lyrics": "שמץ", "chords": "C" }, { "lyrics": "לראותו" }],
  [{ "lyrics": "למקרה", "chords": "Bm" }, { "lyrics": "שייתקל" }],
  [{ "lyrics": "פתע", "chords": "Am" }, { "lyrics": "במותו" }],
  [
    { "lyrics": "הולך" },
    { "lyrics": "בטל,", "chords": "D" },
    { "lyrics": "הולך", "chords": "F#m" }
  ],
  [{ "lyrics": "הולך" }, { "lyrics": "בטל" }]
]
